pianola/__init__.py
pianola/__main__.py
pianola/scene.py
pianola/resources/images/logo.png
pianola/resources/shaders/pianola.frag
pianola-0.9.1.dist-info/METADATA
pianola-0.9.1.dist-info/WHEEL
pianola-0.9.1.dist-info/entry_points.txt
pianola-0.9.1.dist-info/RECORD
