Metadata-Version: 2.4
Name: pianola
Version: 0.9.1
Summary: 🎹 World's finest piano roll visualizer, where elegance meets motion
Project-URL: GitHub, https://github.com/BrokenSource/Pianola
Project-URL: Changelog, https://pianola.brokensrc.dev/about/changelog
Project-URL: Funding, https://pianola.brokensrc.dev/about/sponsors
Project-URL: Contact, https://pianola.brokensrc.dev/about/contact
Project-URL: Docs, https://pianola.brokensrc.dev/docs
Project-URL: Download, https://pianola.brokensrc.dev/get
Project-URL: Homepage, https://pianola.brokensrc.dev
Author-email: Tremeschin <29046864+Tremeschin@users.noreply.github.com>
License-Expression: AGPL-3.0
Requires-Python: >=3.10
Requires-Dist: broken-source==0.9.1
Requires-Dist: shaderflow==0.9.1
